spacexPython-1.0.1.dist-info/METADATA
spacexPython-1.0.1.dist-info/RECORD
spacexPython-1.0.1.dist-info/WHEEL
spacexPython-1.0.1.dist-info/entry_points.txt
spacexPython-1.0.1.dist-info/top_level.txt
spacexpython/__init__.py
spacexpython/launches.py
spacexpython/rockets.py
spacexpython/spacex.py
spacexpython/url.py
spacexpython/urldata.py
