Metadata-Version: 2.1
Name: spacexPython
Version: 1.0.1
Summary: Simple Python wrapper for the SpaceX API
Home-page: UNKNOWN
Author: Vinay Phadnis
Author-email: phadnisvinay30@gmail.com
License: MIT
Keywords: wrapper api spacex
Platform: UNKNOWN
Requires-Dist: requests
